Metadata-Version: 1.2
Name: pybfilter
Version: 0.1
Summary: python3 Bloom Filter
Home-page: https://github.com/imagecser/pybfilter
Author: Zhi Sun
Author-email: zhi.suun@gmail.com
License: UNKNOWN
Keywords: Bloom Filter
Platform: UNKNOWN
Classifier: Development Status :: 3 - Alpha
Classifier: Intended Audience :: Developers
Classifier: License :: OSI Approved :: MIT License
Classifier: Programming Language :: Python :: 3
Requires-Python: >=3
